<annotation>
  <folder>VOC2007</folder>
  <filename>1137.jpg</filename>
  <source>
    <database>Coco database</database>
  </source>
  <size>
    <width>640</width>
    <height>512</height>
    <depth>3</depth>
  </size>
  <segmented>0</segmented>
  <object>
    <name>car</name>
    <pose>Unspecified</pose>
    <truncated>0</truncated>
    <difficult>0</difficult>
    <bndbox>
      <xmin>165</xmin>
      <ymin>266</ymin>
      <xmax>183</xmax>
      <ymax>305</ymax>
    </bndbox>
  </object>
  <object>
    <name>car</name>
    <pose>Unspecified</pose>
    <truncated>0</truncated>
    <difficult>0</difficult>
    <bndbox>
      <xmin>144</xmin>
      <ymin>324</ymin>
      <xmax>161</xmax>
      <ymax>371</ymax>
    </bndbox>
  </object>
</annotation>
