<annotation>
  <folder>VOC2007</folder>
  <filename>720.jpg</filename>
  <source>
    <database>Coco database</database>
  </source>
  <size>
    <width>640</width>
    <height>512</height>
    <depth>3</depth>
  </size>
  <segmented>0</segmented>
  <object>
    <name>car</name>
    <pose>Unspecified</pose>
    <truncated>0</truncated>
    <difficult>0</difficult>
    <bndbox>
      <xmin>360</xmin>
      <ymin>219</ymin>
      <xmax>386</xmax>
      <ymax>270</ymax>
    </bndbox>
  </object>
  <object>
    <name>car</name>
    <pose>Unspecified</pose>
    <truncated>0</truncated>
    <difficult>0</difficult>
    <bndbox>
      <xmin>357</xmin>
      <ymin>126</ymin>
      <xmax>385</xmax>
      <ymax>184</ymax>
    </bndbox>
  </object>
</annotation>
